nonebot_plugin_bilibili_notifier/__init__.py
nonebot_plugin_bilibili_notifier/config.py
nonebot_plugin_bilibili_notifier-0.2.2.dist-info/WHEEL
nonebot_plugin_bilibili_notifier-0.2.2.dist-info/METADATA
nonebot_plugin_bilibili_notifier-0.2.2.dist-info/licenses/LICENSE
nonebot_plugin_bilibili_notifier-0.2.2.dist-info/RECORD
