Metadata-Version: 2.1
Name: nonebot-plugin-bilibili-notifier
Version: 0.2.2
Summary: NoneBot2 plugin for pushing update and live notifications from Bibibili.
License: MIT
Author-email: Variante <382086919@qq.com>
Requires-Python: >=3.8
Requires-Dist: bilibili-api-python>=16.2.0
Requires-Dist: nonebot-adapter-onebot>=2.1.5
Requires-Dist: nonebot-plugin-apscheduler>=0.2.0
Requires-Dist: nonebot-plugin-send-anything-anywhere
Requires-Dist: nonebot2>=2.0.0rc2
Requires-Dist: nonebot_plugin_localstore
Project-URL: Homepage, https://github.com/Variante/nonebot-plugin-bilibili-notifier
Project-URL: Repository, https://github.com/Variante/nonebot-plugin-bilibili-notifier
